oemof/tabular/__init__.py
oemof/tabular/__main__.py
oemof/tabular/_facade.py
oemof/tabular/cli.py
oemof/tabular/constraint_facades.py
oemof/tabular/facades.py
oemof/tabular/config/__init__.py
oemof/tabular/config/config.py
oemof/tabular/config/foreign_key_descriptors.json
oemof/tabular/config/foreign_keys.json
oemof/tabular/data/data.xls
oemof/tabular/datapackage/__init__.py
oemof/tabular/datapackage/aggregation.py
oemof/tabular/datapackage/building.py
oemof/tabular/datapackage/processing.py
oemof/tabular/datapackage/reading.py
oemof/tabular/examples/datapackages/build_datapackage_goal/datapackage.json
oemof/tabular/examples/datapackages/build_datapackage_goal/data/elements/.gitkeep
oemof/tabular/examples/datapackages/build_datapackage_goal/data/elements/bus.csv
oemof/tabular/examples/datapackages/build_datapackage_goal/data/elements/modex_tech_generator_gas.csv
oemof/tabular/examples/datapackages/build_datapackage_goal/data/elements/modex_tech_storage_battery.csv
oemof/tabular/examples/datapackages/build_datapackage_goal/data/elements/modex_tech_wind_turbine_onshore.csv
oemof/tabular/examples/datapackages/build_datapackage_goal/data/periods/periods.csv
oemof/tabular/examples/datapackages/build_datapackage_goal/data/sequences/.gitkeep
oemof/tabular/examples/datapackages/build_datapackage_goal/data/sequences/modex_tech_wind_turbine_onshore_sequence.csv
oemof/tabular/examples/datapackages/dispatch/README.md
oemof/tabular/examples/datapackages/dispatch/datapackage.json
oemof/tabular/examples/datapackages/dispatch/data/elements/bus.csv
oemof/tabular/examples/datapackages/dispatch/data/elements/dispatchable.csv
oemof/tabular/examples/datapackages/dispatch/data/elements/link.csv
oemof/tabular/examples/datapackages/dispatch/data/elements/load.csv
oemof/tabular/examples/datapackages/dispatch/data/elements/storage.csv
oemof/tabular/examples/datapackages/dispatch/data/elements/volatile.csv
oemof/tabular/examples/datapackages/dispatch/data/sequences/load_profile.csv
oemof.tabular-0.0.5.dist-info/AUTHORS.rst
oemof.tabular-0.0.5.dist-info/LICENSE
oemof.tabular-0.0.5.dist-info/METADATA
oemof.tabular-0.0.5.dist-info/WHEEL
oemof.tabular-0.0.5.dist-info/entry_points.txt
oemof.tabular-0.0.5.dist-info/top_level.txt
oemof.tabular-0.0.5.dist-info/RECORD
