Metadata-Version: 2.1
Name: oemof.tabular
Version: 0.0.5
Summary: Load oemof energy systems from tabular data sources.
Home-page: https://github.com/oemof/oemof-tabular
Author: Stephan Günther, Simon Hilpert, Martin Söthe, Jann Launer, Hendrik Huyskens, Julian Endres, Felix Maurer
Author-email: gnn.code@gmail.com
License: BSD 3-Clause License
Classifier: Development Status :: 2 - Pre-Alpha
Classifier: Intended Audience :: Developers
Classifier: License :: OSI Approved :: BSD License
Classifier: Operating System :: Unix
Classifier: Operating System :: POSIX
Classifier: Operating System :: Microsoft :: Windows
Classifier: Programming Language :: Python
Classifier: Programming Language :: Python :: 3
Classifier: Programming Language :: Python :: 3.9
Classifier: Programming Language :: Python :: 3.10
Classifier: Programming Language :: Python :: Implementation :: CPython
Classifier: Topic :: Utilities
Requires-Python: >=3.9, <3.11
License-File: LICENSE
License-File: AUTHORS.rst
Requires-Dist: datapackage ==1.5.1
Requires-Dist: tableschema ==1.7.4
Requires-Dist: oemof.solph ==0.5.2.dev1
Requires-Dist: pandas >=0.22
Requires-Dist: oemof.network ==0.5.0a4
Requires-Dist: paramiko
Requires-Dist: toml
Provides-Extra: aggregation
Requires-Dist: tsam ; extra == 'aggregation'
Provides-Extra: cli
Requires-Dist: click ; extra == 'cli'
Provides-Extra: dev
Requires-Dist: pytest ; extra == 'dev'
Requires-Dist: black ; extra == 'dev'
Requires-Dist: isort ; extra == 'dev'
Requires-Dist: flake8 ; extra == 'dev'
Provides-Extra: geometry
Requires-Dist: shapely ; extra == 'geometry'
Requires-Dist: scipy ; extra == 'geometry'
Requires-Dist: pyproj ; extra == 'geometry'
Requires-Dist: geojson ; extra == 'geometry'
Requires-Dist: pyshp ; extra == 'geometry'
Provides-Extra: plots
Requires-Dist: plotly ; extra == 'plots'
Requires-Dist: matplotlib ; extra == 'plots'
